spoko_kawal/__init__.py
spoko_kawal-0.0.dist-info/METADATA
spoko_kawal-0.0.dist-info/WHEEL
spoko_kawal-0.0.dist-info/top_level.txt
spoko_kawal-0.0.dist-info/RECORD
