Metadata-Version: 2.1
Name: spoko-kawal
Version: 0.0
Summary: Tells a funniest joke ever!
Home-page: UNKNOWN
Author-email: tomek.juszczyszyn@gmail.com
License: UNKNOWN
Platform: UNKNOWN
